overssh/__init__.py
overssh/__init__.pyi
overssh/__version__.py
overssh/__version__.pyi
overssh/aliases.py
overssh/aliases.pyi
overssh/auth.py
overssh/auth.pyi
overssh/py.typed
overssh/sftp.py
overssh/sftp.pyi
overssh-0.0.2.dist-info/LICENSE
overssh-0.0.2.dist-info/METADATA
overssh-0.0.2.dist-info/WHEEL
overssh-0.0.2.dist-info/top_level.txt
overssh-0.0.2.dist-info/RECORD
