Metadata-Version: 2.1
Name: overssh
Version: 0.0.2
Summary: <PROJECT_DESCRIPTION>
Home-page: https://github.com/rilshok/overssh
Author: Vladislav A. Proskurov
Author-email: rilshok@pm.me
License: MIT
Platform: UNKNOWN
Classifier: Programming Language :: Python :: 3.9
Classifier: License :: OSI Approved :: MIT License
Classifier: Operating System :: OS Independent
Classifier: Development Status :: 1 - Planning
Requires-Python: >=3.9
License-File: LICENSE
Requires-Dist: pytest
Requires-Dist: paramiko
Requires-Dist: pysftp
